multitracker/__init__.py
multitracker/auto_annotate_pro.py
multitracker/config.py
multitracker/core/__init__.py
multitracker/core/dataset_manager.py
multitracker/core/video_utils.py
multitracker/core/detection/__init__.py
multitracker/core/io/__init__.py
multitracker/core/io/cached_video_reader.py
multitracker/core/io/multi_video_manager.py
multitracker/core/tracker/__init__.py
multitracker/core/tracker/multi_tracker.py
multitracker/core/visualization/__init__.py
multitracker/core/visualization/plot_bounding_boxes.py
multitracker/core/visualization/track_color_map.py
multitracker/qt/__init__.py
multitracker/qt/my_main_window.py
multitrackpro-0.1.3.data/scripts/auto_annotate_pro.py
multitrackpro-0.1.3.dist-info/AUTHORS.rst
multitrackpro-0.1.3.dist-info/LICENSE
multitrackpro-0.1.3.dist-info/METADATA
multitrackpro-0.1.3.dist-info/WHEEL
multitrackpro-0.1.3.dist-info/entry_points.txt
multitrackpro-0.1.3.dist-info/top_level.txt
multitrackpro-0.1.3.dist-info/RECORD
