Metadata-Version: 2.1
Name: multitrackpro
Version: 0.1.3
Summary: A multi-camera multi-object tracking software with its own labelling tool to annotate datasets.
Home-page: https://github.com/saurabheights/multitrackpro
Author: Saurabh Khanduja
Author-email: pixelperceive@gmail.com
License: GNU General Public License v3
Keywords: multitrackpro,annotation,labelling,machine-learning,deep-learning,vision,ML,DL,AI,YOLO
Classifier: Development Status :: 2 - Pre-Alpha
Classifier: Intended Audience :: Developers
Classifier: Intended Audience :: Education
Classifier: Intended Audience :: Science/Research
Classifier: License :: OSI Approved :: GNU General Public License v3 (GPLv3)
Classifier: Natural Language :: English
Classifier: Programming Language :: Python :: 3
Classifier: Programming Language :: Python :: 3.6
Classifier: Programming Language :: Python :: 3.7
Classifier: Programming Language :: Python :: 3.8
Classifier: Programming Language :: Python :: 3.9
Classifier: Programming Language :: Python :: 3.10
Classifier: Topic :: Software Development
Classifier: Topic :: Scientific/Engineering
Classifier: Topic :: Scientific/Engineering :: Artificial Intelligence
Classifier: Topic :: Scientific/Engineering :: Image Recognition
Classifier: Topic :: Scientific/Engineering :: Image Processing
Requires-Python: >=3.6
License-File: LICENSE
License-File: AUTHORS.rst
Requires-Dist: ultralytics (>=8.0.125)
Requires-Dist: linetimer (>=0.1.5)
Requires-Dist: opencv-python (>=4.7.0)
Requires-Dist: pyqt6 (>=6.5.1)
